{
  "REDSHIFT": {
    "sourceType": "REDSHIFT", "tags":["beta"],
    "metadataRefresh": {"datasetDiscovery": true},
    "form": { "tabs": [
      {
        "name": "General",
        "isGeneral": true,
        "sections": [
          {
            "name": "Connection",
            "elements": [
              {
                "propName": "config.connectionString",
                "placeholder": "e.g. jdbc:redshift://123.123.123.123:5439/database",
                "help": {"position":"bottom", "text": "Your JDBC connection URL can be found in AWS console"},
                "validate": {"isRequired": true}
              }
            ]
          },
          {
            "name": "Authentication",
            "elements": [
              {
                "propName": "config.authenticationType"
              }
            ]
          }
        ]
      },
      {
        "name": "Advanced Options",
        "sections": [
          {
            "elements": [
              {
                "propName": "config.fetchSize",
                "size": "half",
                "value": "0",
                "tooltip": "Number of records to fetch at once.",
                "help": {"position": "bottom", "text": "Set to 0 to have Dremio automatically decide."}
              },
              {
                "propName": "config.useLegacyDialect"
              }
            ]
          }
        ]
      }
    ]
  }},
  "MSSQL": {
    "sourceType": "MSSQL",
    "metadataRefresh": {"datasetDiscovery": true},
    "form": {"tabs": [
      {
        "name": "General",
        "isGeneral": true,
        "sections": [
          {
            "name": "Connection",
            "layout": "row",
            "elements": [
              {
                "propName": "config.hostname",
                "placeholder": "e.g.123.123.123.123",
                "size": "half",
                "validate": {"isRequired": true}
              },
              {
                "propName": "config.port",
                "size": "half"
              },
              {
                "propName": "config.database"
              }
            ]
          },
          {
            "name": "Authentication",
            "elements": [
              {
                "propName": "config.authenticationType"
              }
            ]
          },
          {
            "propName": "config.useSsl",
            "tooltip": "Encryption validation mode can be customized under Advanced Options > Encryption"
          }
        ]
      },
      {
        "name": "Advanced Options",
        "sections": [
          {
            "elements": [
              {
                "propName": "config.showOnlyConnectionDatabase"
              },
              {
                "propName": "config.fetchSize",
                "size": "half",
                "tooltip": "Number of records to fetch at once.",
                "help": {"position": "bottom", "text": "Set to 0 to have Dremio automatically decide."}
              },
              {
                "propName": "config.useLegacyDialect"
              }
            ]
          },
          {
            "name": "Encryption",
            "elements": [
              {
                "uiType": "check_enabled_container",
                "propName": "config.enableServerVerification",
                "checkValue": true,
                "tooltip": "Verify SQL Server instance when using encrypted connections.",
                "container": {
                  "propName": "config.hostnameOverride",
                  "placeholder": "eg my.sqlserver.com",
                  "tooltip": "Use this field to specify a hostname in the SSL certificate that differs from the server name. Leave this field blank if the hostname in the certificate matches the server name."
                }
              }
            ]
          }
        ]
      }
    ]
  }},
  "MONGO": {
    "sourceType": "MONGO", "tags": ["beta"],
    "metadataRefresh": {"datasetDiscovery": true},
    "form": {"tabs": [
      {
        "name": "General",
        "isGeneral": true,
        "sections": [
          {
            "name": "Connection",
            "help": {"position": "top", "text": "If MongoDB is sharded, enter the mongos hosts. Otherwise, enter the mongod host."},
            "elements": [
              {
                "propName": "config.hostList",
                "uiType": "host_list",
                "emptyLabel": "",
                "addLabel": "Add Host",
                "defaultPort": 27017
              },
              {
                "tooltip": "Force encrypted connection over SSL",
                "propName": "config.useSsl"
              },
              {
                "tooltip": "If enabled, queries will fail if no secondaries are available.",
                "propName": "config.secondaryReadsOnly"
              }
            ]
          },
          {
            "name": "Authentication",
            "elements": [
              {
                "propName": "config.authenticationType"
              },
              {
                "propName": "config.authDatabase"
              }
            ]
          }
        ]
      },
      {
        "name": "Advanced Options",
        "sections": [
          {
            "elements": [
              {
                "propName": "config.subpartitionSize",
                "tooltip": "Number of records to be read by query fragments (increases query parallelism). Ignored if value is zero.",
                "size": "half",
                "validate": {"isNumber": true}
              },
              {
                "propName": "config.authenticationTimeoutMillis",
                "tooltip": "Default is 2000 milliseconds",
                "size": "half",
                "validate": {"isNumber": true}
              }
            ]
          },
          {
            "name": "Connection Properties",
            "elements": [
              {
                "emptyLabel": "No properties added",
                "addLabel": "Add property",
                "propName": "config.propertyList"
              }
            ]
          }
        ]
      }
    ]
  }},
  "MYSQL": {
    "sourceType": "MYSQL",
    "metadataRefresh": {"datasetDiscovery": true},
    "form": {"tabs": [
      {
        "name": "General",
        "isGeneral": true,
        "sections": [
          {
            "name": "Connection",
            "layout": "row",
            "elements": [
              {
                "propName": "config.hostname",
                "placeholder": "e.g.123.123.123.123",
                "size": "half",
                "validate": {"isRequired": true}
              },
              {
                "propName": "config.port",
                "size": "half",
                "validate": {"isRequired": true}
              },
              {
                "propName": "config.database"
              }
            ]
          },
          {
            "name": "Authentication",
            "elements": [
              {
                "propName": "config.authenticationType"
              }
            ]
          }
        ]
      },
      {
        "name": "Advanced Options",
        "sections": [
          {
            "help": {"position": "bottom", "text": "Set to 0 to have Dremio automatically decide."},
            "elements": [
              {
                "propName": "config.showOnlyConnectionDatabase"
              },
              {
                "propName": "config.netWriteTimeout",
                "size": "half",
                "tooltip": "Seconds to wait for data from the server before aborting the connection."
              },
              {
                "propName": "config.fetchSize",
                "size": "half",
                "tooltip": "Number of records to fetch at once."
              },
              {
                "propName": "config.useLegacyDialect"
              }
            ]
          }
        ]
      }
    ]
  }},
  "ORACLE": {
    "sourceType": "ORACLE",
    "metadataRefresh": {"datasetDiscovery": true},
    "form": {"tabs": [
      {
        "name": "General",
        "isGeneral": true,
        "sections": [
          {
            "name": "Connection",
            "layout": "row",
            "elements": [
              {
                "propName": "config.hostname",
                "placeholder": "e.g.123.123.123.123",
                "size": "half",
                "validate": {"isRequired": true}
              },
              {
                "propName": "config.port",
                "size": "half",
                "validate": {"isRequired": true}
              },
              {
                "propName": "config.instance",
                "size": "full",
                "validate": {"isRequired": true}
              },
              {
                "propName": "config.useSsl",
                "size": "full",
                "tooltip": "Encryption validation mode can be customized under Advanced Options > Encryption"
              }
            ]
          },
          {
            "name": "Authentication",
            "elements": [
              {
                "propName": "config.authenticationType"
              }
            ]
          }
        ]
      },
      {
        "name": "Advanced Options",
        "sections": [
          {
            "elements": [
              {
                "propName": "config.useTimezoneAsRegion",
                "size": "half",
                "tooltip": "If checked, use timezone to set connection region."
              },
              {
                "propName": "config.includeSynonyms",
                "size": "half",
                "tooltip": "If checked, include synonyms as datasets."
              },
              {
                "propName": "config.fetchSize",
                "size": "half",
                "tooltip": "Number of records to fetch at once.",
                "help": {"position": "bottom", "text": "Set to 0 to have Dremio automatically decide."}
              },
              {
                "propName": "config.useLegacyDialect"
              }
            ]
          },
          {
            "name": "Encryption",
            "elements": [
              {
                "propName": "config.sslServerCertDN",
                "size": "half",
                "tooltip": "Certificate Distinguished Name. Leave blank to disable DN match"
              }
            ]
          }
        ]
      }
    ]
  }},
  "POSTGRES": {
    "sourceType": "POSTGRES",
    "metadataRefresh": {"datasetDiscovery": true},
    "form": {"tabs": [
      {
        "name": "General",
        "isGeneral": true,
        "sections": [
          {
            "name": "Connection",
            "layout": "row",
            "elements": [
              {
                "propName": "config.hostname",
                "placeholder": "e.g.123.123.123.123",
                "size": "half",
                "validate": {"isRequired": true}
              },
              {
                "propName": "config.port",
                "size": "half",
                "validate": {"isRequired": true}
              },
              {
                "propName": "config.databaseName",
                "size": "full",
                "validate": {"isRequired": true}
              },
              {
                "propName": "config.useSsl",
                "tooltip": "Encryption validation mode can be customized under Advanced Options > Encryption"
              }
            ]
          },
          {
            "name": "Authentication",
            "elements": [
              {
                "propName": "config.authenticationType"
              }
            ]
          }
        ]
      },
      {
        "name": "Advanced Options",
        "sections": [
          {
            "elements": [
              {
                "propName": "config.fetchSize",
                "size": "half",
                "tooltip": "Number of records to fetch at once.",
                "help": {"position": "bottom", "text": "Set to 0 to have Dremio automatically decide."}
              },
              {
                "propName": "config.useLegacyDialect"
              }
            ]
          },
          {
            "name": "Encryption",
            "elements": [
              {
                "propName": "config.encryptionValidationMode",
                "tooltip": "In Postgres terminology for 'sslmode', these map to 'verify-full', 'verify-ca' and 'require' respectively. "
              }
            ]
          }
        ]
      }
    ]
  }},
  "TERADATA": {
    "sourceType": "TERADATA",
    "metadataRefresh": {"datasetDiscovery": true},
    "form": {"tabs": [
      {
        "name": "General",
        "isGeneral": true,
        "sections": [
          {
            "name": "Connection",
            "layout": "row",
            "elements": [
              {
                "propName": "config.hostname",
                "placeholder": "e.g.123.123.123.123",
                "size": "half",
                "validate": {"isRequired": true}
              },
              {
                "propName": "config.port",
                "size": "half",
                "validate": {"isRequired": true}
              },
              {
                "propName": "config.database",
                "validate": {"isRequired": true}
              }
            ]
          },
          {
            "name": "Authentication",
            "elements": [
              {
                "propName": "config.authenticationType"
              }
            ]
          },
          {
            "propName": "config.useSsl",
            "tooltip": "Force connections to Teradata to be encrypted. Note that if this setting is off, encryption can still be enabled automatically if the Teradata server requires it."
          }
        ]
      },
      {
        "name": "Advanced Options",
        "sections": [
          {
            "elements": [
              {
                "propName": "config.showOnlyConnectionDatabase"
              },
              {
                "propName": "config.fetchSize",
                "size": "half",
                "tooltip": "Number of records to fetch at once.",
                "help": {"position": "bottom", "text": "Set to 0 to have Dremio automatically decide."}
              }
            ]
          }
        ]
      }
    ]
  }}
}
